superalgo/__init__.py
superalgo/search.py
superalgo/sort.py
superalgo-1.0.1.dist-info/LICENSE
superalgo-1.0.1.dist-info/METADATA
superalgo-1.0.1.dist-info/WHEEL
superalgo-1.0.1.dist-info/top_level.txt
superalgo-1.0.1.dist-info/RECORD
