Metadata-Version: 2.1
Name: superalgo
Version: 1.0.1
Summary: Python sorting and searching algorithms
Home-page: https://github.com/Harvard90873/algorithms
Author: Harvard90873
Author-email: rem.cs90873@gmail.com
License: MIT
Platform: UNKNOWN
Classifier: License :: OSI Approved :: MIT License
Classifier: Programming Language :: Python :: 3.9
Classifier: Programming Language :: Python :: 3
Requires-Dist: data-structures3x
